minhtml/__init__.py
minhtml/cli.py
minhtml/minhtml.py
minhtml-0.1.1.dist-info/METADATA
minhtml-0.1.1.dist-info/WHEEL
minhtml-0.1.1.dist-info/entry_points.txt
minhtml-0.1.1.dist-info/licenses/AUTHORS.rst
minhtml-0.1.1.dist-info/licenses/LICENSE
minhtml-0.1.1.dist-info/RECORD
